seatools/ioc/server/__init__.py
seatools/ioc/server/app.py
seatools/ioc/starters/flask/__init__.py
seatools/ioc/starters/flask/base.py
seatools_starter_web_flask-1.0.2.dist-info/METADATA
seatools_starter_web_flask-1.0.2.dist-info/WHEEL
seatools_starter_web_flask-1.0.2.dist-info/licenses/LICENSE
seatools_starter_web_flask-1.0.2.dist-info/RECORD
