Metadata-Version: 2.4
Name: seatools-starter-web-flask
Version: 1.0.2
Summary: Seatools Flask Web Starter
Project-URL: Homepage, https://github.com/seatools-py/seatools-starter-web-flask
Project-URL: Issues, https://github.com/seatools-py/seatools-starter-web-flask/issues
Author-email: seatools-py <521274311@qq.com>
License-Expression: MIT
License-File: LICENSE
Keywords: seatools>=1.0.41,starter
Classifier: License :: OSI Approved :: MIT License
Classifier: Operating System :: OS Independent
Classifier: Programming Language :: Python :: 3
Requires-Python: >=3.9
Requires-Dist: flask
Requires-Dist: seatools
